README.rst
setup.py
django_starken.egg-info/PKG-INFO
django_starken.egg-info/SOURCES.txt
django_starken.egg-info/dependency_links.txt
django_starken.egg-info/requires.txt
django_starken.egg-info/top_level.txt
starken/connector.py
starken/handler.py
starken/settings.py