Metadata-Version: 2.1
Name: django-starken
Version: 1.0.5
Summary: Django Starken Integration
Home-page: https://gitlab.com/linets/ecommerce/oms/integrations/django-starken/
Author: Linets Development Team
Author-email: dteam@linets.cl
License: MIT
Platform: UNKNOWN
Requires-Python: >=3.7
